{
  "answer": "A mitochondrion has a double membrane and is generally described as having an oval or bean shape [Page 3]. Its structure includes several parts:\n\n*   **Outer membrane:** This boundary is smooth and permeable to small molecules [Page 3].\n*   **Inner membrane:** This membrane is folded into structures called cristae and is the site where ATP synthesis occurs [Page 3].\n*   **Intermembrane space:** This is the area located between the two membranes [Page 3].\n*   **Matrix:** This central space, which is enclosed by the inner membrane, contains enzymes necessary for the Krebs cycle [Page 3].",
  "citations": [
    {
      "page": 3
    }
  ],
  "not_in_book": false,
  "pages_used": [
    1,
    2,
    3
  ]
}